chesssnake/__init__.py
chesssnake/chesslib/Chess.py
chesssnake/chesslib/ChessError.py
chesssnake/chesslib/ChessImg.py
chesssnake/chesslib/Game.py
chesssnake/chesslib/__init__.py
chesssnake/data/Roboto-Black.ttf
chesssnake/data/init.sql
chesssnake/data/img/0.png
chesssnake/data/img/1.png
chesssnake/data/img/B0.png
chesssnake/data/img/B1.png
chesssnake/data/img/K0.png
chesssnake/data/img/K1.png
chesssnake/data/img/N0.png
chesssnake/data/img/N1.png
chesssnake/data/img/P0.png
chesssnake/data/img/P1.png
chesssnake/data/img/Q0.png
chesssnake/data/img/Q1.png
chesssnake/data/img/R0.png
chesssnake/data/img/R1.png
chesssnake/data/img/a.png
chesssnake/data/img/b.png
chesssnake/data/img/blankboard.png
chesssnake/data/img/c.png
chesssnake/data/img/d.png
chesssnake/data/img/e.png
chesssnake/data/img/f.png
chesssnake/data/img/g.png
chesssnake/data/img/h.png
chesssnake/data/img/num1.png
chesssnake/data/img/num2.png
chesssnake/data/img/num3.png
chesssnake/data/img/num4.png
chesssnake/data/img/num5.png
chesssnake/data/img/num6.png
chesssnake/data/img/num7.png
chesssnake/data/img/num8.png
chesssnake/data/img/orange.png
chesssnake/data/img/template.png
chesssnake/postgres/Game.py
chesssnake/postgres/GameError.py
chesssnake/postgres/Sql_Utils.py
chesssnake/postgres/__init__.py
chesssnake-0.5.1.dist-info/LICENSE
chesssnake-0.5.1.dist-info/METADATA
chesssnake-0.5.1.dist-info/WHEEL
chesssnake-0.5.1.dist-info/top_level.txt
chesssnake-0.5.1.dist-info/RECORD
