Metadata-Version: 2.1
Name: chesssnake
Version: 0.5.1
Summary: A Python library for playing, visualizing, and storing chess games.
Home-page: https://github.com/GabeBecker2048/chesssnake
Author: Gabe Becker
Author-email: gabebecker2048@gmail.com
License: MIT
Classifier: Programming Language :: Python :: 3.9
Classifier: Programming Language :: Python :: 3.10
Classifier: Programming Language :: Python :: 3.11
Classifier: Programming Language :: Python :: 3.12
Classifier: Programming Language :: Python :: 3.13
Classifier: License :: OSI Approved :: MIT License
Classifier: Operating System :: OS Independent
Requires-Python: >=3.9
License-File: LICENSE
Requires-Dist: pillow~=10.4.0
Provides-Extra: postgres
Requires-Dist: psycopg2~=2.9.9; extra == "postgres"
Provides-Extra: postgres-binary
Requires-Dist: psycopg2-binary~=2.9.9; extra == "postgres-binary"
